pyhfapi/__init__.py
pyhfapi/_base_client.py
pyhfapi/_client.py
pyhfapi/_compat.py
pyhfapi/_constants.py
pyhfapi/_exceptions.py
pyhfapi/_files.py
pyhfapi/_models.py
pyhfapi/_qs.py
pyhfapi/_resource.py
pyhfapi/_response.py
pyhfapi/_streaming.py
pyhfapi/_types.py
pyhfapi/_version.py
pyhfapi/py.typed
pyhfapi/_utils/__init__.py
pyhfapi/_utils/_compat.py
pyhfapi/_utils/_datetime_parse.py
pyhfapi/_utils/_logs.py
pyhfapi/_utils/_proxy.py
pyhfapi/_utils/_reflection.py
pyhfapi/_utils/_resources_proxy.py
pyhfapi/_utils/_streams.py
pyhfapi/_utils/_sync.py
pyhfapi/_utils/_transform.py
pyhfapi/_utils/_typing.py
pyhfapi/_utils/_utils.py
pyhfapi/lib/.keep
pyhfapi/resources/__init__.py
pyhfapi/resources/ask_access.py
pyhfapi/resources/datasets.py
pyhfapi/resources/resolve.py
pyhfapi/resources/spaces.py
pyhfapi/resources/user_access_report.py
pyhfapi/resources/api/__init__.py
pyhfapi/resources/api/api.py
pyhfapi/resources/api/discussions.py
pyhfapi/resources/api/docs.py
pyhfapi/resources/api/jobs.py
pyhfapi/resources/api/notifications.py
pyhfapi/resources/api/repos.py
pyhfapi/resources/api/resolve_cache.py
pyhfapi/resources/api/scheduled_jobs.py
pyhfapi/resources/api/blog/__init__.py
pyhfapi/resources/api/blog/blog.py
pyhfapi/resources/api/blog/comment/__init__.py
pyhfapi/resources/api/blog/comment/comment.py
pyhfapi/resources/api/blog/comment/reply.py
pyhfapi/resources/api/collections/__init__.py
pyhfapi/resources/api/collections/collections.py
pyhfapi/resources/api/collections/items.py
pyhfapi/resources/api/datasets/__init__.py
pyhfapi/resources/api/datasets/branch.py
pyhfapi/resources/api/datasets/datasets.py
pyhfapi/resources/api/datasets/lfs_files.py
pyhfapi/resources/api/datasets/resource_group.py
pyhfapi/resources/api/datasets/tag.py
pyhfapi/resources/api/datasets/user_access_request.py
pyhfapi/resources/api/models/__init__.py
pyhfapi/resources/api/models/branch.py
pyhfapi/resources/api/models/lfs_files.py
pyhfapi/resources/api/models/models.py
pyhfapi-1.1.0.dist-info/METADATA
pyhfapi-1.1.0.dist-info/WHEEL
pyhfapi-1.1.0.dist-info/licenses/LICENSE
pyhfapi-1.1.0.dist-info/RECORD
